<?xml version="1.0"?>
<?xml-stylesheet type="text/xsl" href="configuration.xsl"?>
<!--
/**
 * Licensed to the Apache Software Foundation (ASF) under one
 * or more contributor license agreements.  See the NOTICE file
 * distributed with this work for additional information
 * regarding copyright ownership.  The ASF licenses this file
 * to you under the Apache License, Version 2.0 (the
 * "License"); you may not use this file except in compliance
 * with the License.  You may obtain a copy of the License at
 *
 *     http://www.apache.org/licenses/LICENSE-2.0
 *
 * Unless required by applicable law or agreed to in writing, software
 * distributed under the License is distributed on an "AS IS" BASIS,
 * WITHOUT WARRANTIES OR CONDITIONS OF ANY KIND, either express or implied.
 * See the License for the specific language governing permissions and
 * limitations under the License.
 */
-->

<!-- This is a special config file for properties used to monitor status of the service -->
<configuration supports_adding_forbidden="true">

  <!-- log4j.xml -->

  <property>
    <name>content</name>
    <description>This is the jinja template for log4j.xml file for logsearch server</description>
    <value>&lt;?xml version="1.0" encoding="UTF-8" ?&gt;
&lt;!--
  Licensed to the Apache Software Foundation (ASF) under one or more
  contributor license agreements.  See the NOTICE file distributed with
  this work for additional information regarding copyright ownership.
  The ASF licenses this file to You under the Apache License, Version 2.0
  (the "License"); you may not use this file except in compliance with
  the License.  You may obtain a copy of the License at

      http://www.apache.org/licenses/LICENSE-2.0

  Unless required by applicable law or agreed to in writing, software
  distributed under the License is distributed on an "AS IS" BASIS,
  WITHOUT WARRANTIES OR CONDITIONS OF ANY KIND, either express or implied.
  See the License for the specific language governing permissions and
  limitations under the License.
--&gt;
&lt;!DOCTYPE log4j:configuration SYSTEM "log4j.dtd"&gt;
&lt;log4j:configuration xmlns:log4j="http://jakarta.apache.org/log4j/"&gt;
  &lt;appender name="console" class="org.apache.log4j.ConsoleAppender"&gt;
    &lt;param name="Target" value="System.out" /&gt;
    &lt;layout class="org.apache.log4j.PatternLayout"&gt;
      &lt;param name="ConversionPattern" value="%d [%t] %-5p %C{6} (%F:%L) - %m%n" /&gt;
    &lt;/layout&gt;
  &lt;/appender&gt;

  &lt;appender name="rolling_file" class="org.apache.log4j.RollingFileAppender"&gt; 
    &lt;param name="file" value="{{logsearch_log_dir}}/logsearch.log" /&gt; 
    &lt;param name="append" value="true" /&gt; 
    &lt;param name="maxFileSize" value="10MB" /&gt; 
    &lt;param name="maxBackupIndex" value="10" /&gt; 
    &lt;layout class="org.apache.log4j.PatternLayout"&gt; 
      &lt;param name="ConversionPattern" value="%d [%t] %-5p %C{6} (%F:%L) - %m%n"/&gt; 
    &lt;/layout&gt; 
  &lt;/appender&gt;

  &lt;appender name="audit_rolling_file" class="org.apache.log4j.RollingFileAppender"&gt;
    &lt;param name="file" value="{{logsearch_log_dir}}/logsearch-audit.log" /&gt;
    &lt;param name="append" value="true" /&gt;
    &lt;param name="maxFileSize" value="10MB" /&gt;
    &lt;param name="maxBackupIndex" value="10" /&gt;
    &lt;layout class="org.apache.log4j.PatternLayout"&gt;
      &lt;param name="ConversionPattern" value="%d [%t] %-5p %C{6} (%F:%L) - %m%n"/&gt;
    &lt;/layout&gt;
  &lt;/appender&gt;

  &lt;appender name="performance_analyzer" class="org.apache.log4j.RollingFileAppender"&gt;
    &lt;param name="file" value="{{logsearch_log_dir}}/logsearch-performance.log" /&gt;
    &lt;param name="Threshold" value="info" /&gt;
    &lt;param name="append" value="true" /&gt;
    &lt;param name="maxFileSize" value="10MB" /&gt; 
    &lt;param name="maxBackupIndex" value="10" /&gt; 
    &lt;layout class="org.apache.log4j.PatternLayout"&gt;
      &lt;param name="ConversionPattern" value="%d [%t] %-5p %C{6} (%F:%L) - %m%n" /&gt;
    &lt;/layout&gt;
  &lt;/appender&gt;

  &lt;logger name="org.apache.ambari.logsearch.audit" additivity="true"&gt;
    &lt;appender-ref ref="audit_rolling_file" /&gt;
  &lt;/logger&gt;
  
  &lt;logger name="org.apache.ambari.logsearch.performance" additivity="false"&gt;
   &lt;appender-ref ref="performance_analyzer" /&gt;
  &lt;/logger&gt;

  &lt;category name="org.apache.ambari.logsearch" additivity="false"&gt;
    &lt;priority value="info" /&gt;
    &lt;appender-ref ref="rolling_file" /&gt;
  &lt;/category&gt;

  &lt;root&gt;
    &lt;priority value="warn" /&gt;
    &lt;appender-ref ref="rolling_file" /&gt;
  &lt;/root&gt;
&lt;/log4j:configuration&gt;
    </value>
  </property>


</configuration>  
