<?xml version="1.0" encoding="UTF-8"?>
<!--
/**
 * Licensed to the Apache Software Foundation (ASF) under one
 * or more contributor license agreements.  See the NOTICE file
 * distributed with this work for additional information
 * regarding copyright ownership.  The ASF licenses this file
 * to you under the Apache License, Version 2.0 (the
 * "License"); you may not use this file except in compliance
 * with the License.  You may obtain a copy of the License at
 *
 *     http://www.apache.org/licenses/LICENSE-2.0
 *
 * Unless required by applicable law or agreed to in writing, software
 * distributed under the License is distributed on an "AS IS" BASIS,
 * WITHOUT WARRANTIES OR CONDITIONS OF ANY KIND, either express or implied.
 * See the License for the specific language governing permissions and
 * limitations under the License.
 */
-->
<configuration supports_final="true" supports_do_not_extend="true">

  <property>
    <name>ranger_user</name>
    <display-name>Ranger User</display-name>
    <value>ranger</value>
    <on-ambari-upgrade add="true"/>
    <property-type>USER</property-type>
    <description>Ranger username</description>
    <value-attributes>
      <overridable>false</overridable>
    </value-attributes>
  </property>

  <property>
    <name>ranger_group</name>
    <display-name>Ranger Group</display-name>
    <value>ranger</value>
    <on-ambari-upgrade add="true"/>
    <property-type>GROUP</property-type>
    <description>Ranger group</description>
    <value-attributes>
      <type>user</type>
      <overridable>false</overridable>
    </value-attributes>
  </property>

  <property>
    <name>ranger_admin_log_dir</name>
    <value>/var/log/ranger/admin</value>
    <description></description>
    <on-ambari-upgrade add="true"/>
  </property>

  <property>
    <name>ranger_usersync_log_dir</name>
    <value>/var/log/ranger/usersync</value>
    <description></description>
    <on-ambari-upgrade add="true"/>
  </property>

  <property>
    <name>ranger_admin_username</name>
    <value>amb_ranger_admin</value>
    <on-ambari-upgrade add="true"/>
    <property-type>TEXT</property-type>
    <display-name>Ranger Admin username for Ambari</display-name>
    <description>This is the ambari user created for creating repositories and policies in Ranger Admin for each plugin</description>
  </property>

  <property>
    <name>ranger_admin_password</name>
    <display-name>Ranger Admin user's password for Ambari</display-name>
    <value></value>
    <on-ambari-upgrade add="true"/>
    <property-type>PASSWORD</property-type>
    <description>This is the ambari user password created for creating repositories and policies in Ranger Admin for each plugin</description>
    <value-attributes>
      <overridable>false</overridable>
    </value-attributes>
  </property>

  <property>
    <name>admin_username</name>
    <value>admin</value>
    <description>This is the username for default admin user that is used for creating ambari user in Ranger Admin</description>
    <on-ambari-upgrade add="true"/>
  </property>  

  <property>
    <name>admin_password</name>
    <value>admin</value>
    <on-ambari-upgrade add="true"/>
    <property-type>PASSWORD</property-type>
    <description>This is the password for default admin user that is used for creating ambari user in Ranger Admin</description>
  </property>
  
  <property>
    <name>ranger_pid_dir</name>
    <value>/var/run/ranger</value>
    <description></description>
    <on-ambari-upgrade add="true"/>
  </property>

  <property>
    <name>ranger-hdfs-plugin-enabled</name>
    <value>No</value>
    <display-name>HDFS Ranger Plugin</display-name>
    <description>Enable HDFS Ranger plugin</description>
    <on-ambari-upgrade add="true"/>
    <value-attributes>
      <overridable>false</overridable>
      <type>value-list</type>
      <entries>
        <entry>
          <value>Yes</value>
          <label>ON</label>
        </entry>
        <entry>
          <value>No</value>
          <label>OFF</label>
        </entry>
      </entries>
      <selection-cardinality>1</selection-cardinality>
    </value-attributes>
  </property>
  
    <property>
    <name>ranger-yarn-plugin-enabled</name>
    <value>No</value>
    <display-name>YARN Ranger Plugin</display-name>
    <description>Enable YARN Ranger plugin</description>
    <on-ambari-upgrade add="true"/>
    <value-attributes>
      <overridable>false</overridable>
      <type>value-list</type>
      <entries>
        <entry>
          <value>Yes</value>
          <label>ON</label>
        </entry>
        <entry>
          <value>No</value>
          <label>OFF</label>
        </entry>
      </entries>
      <selection-cardinality>1</selection-cardinality>
    </value-attributes>
  </property>

  <property>
    <name>ranger-hive-plugin-enabled</name>
    <value>No</value>
    <display-name>Hive Ranger Plugin</display-name>
    <description>Enable Hive Ranger plugin</description>
    <on-ambari-upgrade add="true"/>
    <value-attributes>
      <overridable>false</overridable>
      <type>value-list</type>
      <entries>
        <entry>
          <value>Yes</value>
          <label>ON</label>
        </entry>
        <entry>
          <value>No</value>
          <label>OFF</label>
        </entry>
      </entries>
      <selection-cardinality>1</selection-cardinality>
    </value-attributes>
  </property>

  <property>
    <name>ranger-hbase-plugin-enabled</name>
    <value>No</value>
    <display-name>Hbase Ranger Plugin</display-name>
    <description>Enable HBase Ranger plugin</description>
    <on-ambari-upgrade add="true"/>
    <value-attributes>
      <overridable>false</overridable>
      <type>value-list</type>
      <entries>
        <entry>
          <value>Yes</value>
          <label>ON</label>
        </entry>
        <entry>
          <value>No</value>
          <label>OFF</label>
        </entry>
      </entries>
      <selection-cardinality>1</selection-cardinality>
    </value-attributes>
  </property>

  <property>
    <name>ranger-knox-plugin-enabled</name>
    <value>No</value>
    <display-name>Knox Ranger Plugin</display-name>
    <description>Enable Knox Ranger plugin</description>
    <on-ambari-upgrade add="true"/>
    <value-attributes>
      <overridable>false</overridable>
      <type>value-list</type>
      <entries>
        <entry>
          <value>Yes</value>
          <label>ON</label>
        </entry>
        <entry>
          <value>No</value>
          <label>OFF</label>
        </entry>
      </entries>
      <selection-cardinality>1</selection-cardinality>
    </value-attributes>
  </property>
  
  <!-- commented the Kafka and Storm plugins as they are not supported
    <property>
    <name>ranger-storm-plugin-enabled</name>
    <value>No</value>
    <display-name>Storm Ranger Plugin</display-name>
    <description>Enable Storm Ranger plugin</description>
    <on-ambari-upgrade add="true"/>
    <value-attributes>
      <overridable>false</overridable>
      <type>value-list</type>
      <entries>
        <entry>
          <value>Yes</value>
          <label>ON</label>
        </entry>
        <entry>
          <value>No</value>
          <label>OFF</label>
        </entry>
      </entries>
      <selection-cardinality>1</selection-cardinality>
    </value-attributes>
  </property>
  
  <property>
    <name>ranger-kafka-plugin-enabled</name>
    <value>No</value>
    <display-name>Kafka Ranger Plugin</display-name>
    <description>Enable Kafka Ranger plugin</description>
    <on-ambari-upgrade add="true"/>
    <value-attributes>
      <overridable>false</overridable>
      <type>value-list</type>
      <entries>
        <entry>
          <value>Yes</value>
          <label>ON</label>
        </entry>
        <entry>
          <value>No</value>
          <label>OFF</label>
        </entry>
      </entries>
      <selection-cardinality>1</selection-cardinality>
    </value-attributes>
  </property>
  --> 
  
  <property>
    <name>bind_anonymous</name>
    <display-name>Bind Anonymous</display-name>
    <value>false</value>
    <value-attributes>
      <type>value-list</type>
      <overridable>false</overridable>
      <entries>
        <entry>
          <value>true</value>
          <label>Yes</label>
        </entry>
        <entry>
          <value>false</value>
          <label>No</label>
        </entry>
      </entries>
      <selection-cardinality>1</selection-cardinality>
      <empty-value-valid>true</empty-value-valid>
    </value-attributes>
    <on-ambari-upgrade add="true"/>
  </property>

  <property>
    <name>xasecure.audit.destination.hdfs</name>
    <value>true</value>
    <display-name>Audit to HDFS</display-name>
    <description>Enable Audit to HDFS for all ranger supported services. This property is overridable at service level</description>
    <on-ambari-upgrade add="true"/>
    <value-attributes>
      <overridable>false</overridable>
      <type>value-list</type>
      <entries>
        <entry>
          <value>true</value>
          <label>ON</label>
        </entry>
        <entry>
          <value>false</value>
          <label>OFF</label>
        </entry>
      </entries>
      <selection-cardinality>1</selection-cardinality>
    </value-attributes>
  </property>

  <property>
    <name>xasecure.audit.destination.hdfs.dir</name>
    <value>hdfs://localhost:8020</value>
    <display-name>Destination HDFS Directory</display-name>
    <description>HDFS folder to write audit to, make sure all service user has required permissions. This property is overridable at service level</description>
    <depends-on>
      <property>
        <type>core-site</type>
        <name>fs.defaultFS</name>
      </property>
    </depends-on>
    <on-ambari-upgrade add="false"/>
  </property>

  <property>
    <name>xasecure.audit.destination.db</name>
    <value>true</value>
    <display-name>Audit to DB</display-name>
    <description>Enable Audit to DB for all ranger supported services. This property is overridable at service level</description>
    <value-attributes>
      <overridable>false</overridable>
      <type>value-list</type>
      <entries>
        <entry>
          <value>true</value>
          <label>ON</label>
        </entry>
        <entry>
          <value>false</value>
          <label>OFF</label>
        </entry>
      </entries>
      <selection-cardinality>1</selection-cardinality>
    </value-attributes>
    <on-ambari-upgrade add="true"/>
  </property>
  
  <!-- Removing auditing to Solr   
  <property>
    <name>xasecure.audit.destination.solr</name>
    <value>true</value>
    <display-name>Audit to Solr</display-name>
    <description>Enable Audit to Solr for all ranger supported services. This property is overridable at service level</description>
    <on-ambari-upgrade add="true"/>
    <value-attributes>
      <overridable>false</overridable>
      <type>value-list</type>
      <entries>
        <entry>
          <value>true</value>
          <label>ON</label>
        </entry>
        <entry>
          <value>false</value>
          <label>OFF</label>
        </entry>
      </entries>
      <selection-cardinality>1</selection-cardinality>
    </value-attributes>
  </property>
  
  <property>
    <name>is_solrCloud_enabled</name>
    <display-name>SolrCloud</display-name>
    <description>SolrCloud uses zookeeper for distributed search and indexing</description>
    <value>false</value>
    <on-ambari-upgrade add="true"/>
    <value-attributes>
      <type>value-list</type>
      <overridable>false</overridable>
      <entries>
        <entry>
          <value>true</value>
          <label>ON</label>
        </entry>
        <entry>
          <value>false</value>
          <label>OFF</label>
        </entry>
      </entries>
      <selection-cardinality>1</selection-cardinality>
      <empty-value-valid>true</empty-value-valid>
    </value-attributes>
  </property>
  --> 
    
 <!-- 
  <property>
    <name>oracle_home</name>
    <deleted>true</deleted>
    <on-ambari-upgrade add="true"/>
  </property>
  -->
  
  <property>
    <name>xml_configurations_supported</name>
    <value>true</value>
    <description></description>
    <on-ambari-upgrade add="true"/>
  </property>
    
  <property>
    <name>ranger_pid_dir</name>
    <value>/var/run/ranger</value>
    <description></description>
    <on-ambari-upgrade add="true"/>
  </property>   
      
  <property>
    <name>create_db_dbuser</name>
    <display-name>Setup Database and Database User</display-name>
    <value>true</value>
    <description>If set to Yes, Ambari will create and setup Ranger Database and Database User. This will require to specify Database Admin user and password</description>
    <on-ambari-upgrade add="true"/>
    <value-attributes>
      <type>value-list</type>
      <overridable>false</overridable>
      <entries>
        <entry>
          <value>true</value>
          <label>Yes</label>
        </entry>
        <entry>
          <value>false</value>
          <label>No</label>
        </entry>
      </entries>
      <selection-cardinality>1</selection-cardinality>
    </value-attributes>
  </property>
  
  <property>
    <name>ranger_privelege_user_jdbc_url</name>
    <display-name>JDBC connect string for root user</display-name>
    <description>JDBC connect string - auto populated based on other values. This is to be used by root user</description>
    <value>jdbc:mysql://localhost</value>
    <value-attributes>
      <overridable>false</overridable>
    </value-attributes>
    <depends-on>
      <property>
        <type>admin-properties</type>
        <name>DB_FLAVOR</name>
      </property>
      <property>
        <type>admin-properties</type>
        <name>db_host</name>
      </property>
    </depends-on>
    <on-ambari-upgrade add="false"/>
  </property>

</configuration>
