{
  "_comment" : "Record format:",
  "_comment" : "blockedRole-blockedCommand: [blockerRole1-blockerCommand1, blockerRole2-blockerCommand2, ...]",
  "general_deps" : {
    "_comment" : "dependencies for all cases",
    "RANGER_SERVICE_CHECK-SERVICE_CHECK" : ["RANGER_ADMIN-START"],
    "RANGER_SERVICE_CHECK-SERVICE_CHECK" : ["RANGER_USERSYNC-START"],
    "RANGER_KMS_SERVER-START" : ["RANGER_ADMIN-START"],
    "RANGER_KMS_SERVICE_CHECK-SERVICE_CHECK" : ["RANGER_KMS_SERVER-START"],
    "HIVE_SERVER-START": ["NODEMANAGER-START", "MYSQL_SERVER-START", "RANGER_USERSYNC-START"],
    "KAFKA_BROKER-START" : ["ZOOKEEPER_SERVER-START", "RANGER_USERSYNC-START", "NAMENODE-START", "METRICS_COLLECTOR-START"],
    "KAFKA_SERVICE_CHECK-SERVICE_CHECK": ["KAFKA_BROKER-START"],
    "RANGER_USERSYNC-START" : ["RANGER_ADMIN-START"],
    "KNOX_GATEWAY-START" : ["RANGER_USERSYNC-START", "NAMENODE-START"],
    "KNOX_SERVICE_CHECK-SERVICE_CHECK" : ["KNOX_GATEWAY-START"],
    "RESOURCEMANAGER-START" : ["RANGER_USERSYNC-START"],
    "HBASE_MASTER-START": ["ZOOKEEPER_SERVER-START", "RANGER_USERSYNC-START"],
    "HIVE_SERVER-START": ["NODEMANAGER-START", "MYSQL_SERVER-START", "RANGER_USERSYNC-START"],
    "ATLAS_SERVICE_CHECK-SERVICE_CHECK": ["ATLAS_SERVER-START"],
    "PHOENIX_QUERY_SERVER-START": ["HBASE_MASTER-START"],
    "OOZIE_SERVER-START": ["FALCON_SERVER-START"],
    "FALCON_SERVICE_CHECK-SERVICE_CHECK": ["FALCON_SERVER-START"],
    "TITAN_SERVICE_CHECK-SERVICE_CHECK": ["HBASE_SERVICE_CHECK-SERVICE_CHECK"]
  },
  "_comment" : "Dependencies that are used when GLUSTERFS is not present in cluster",
  "optional_no_glusterfs": {
    "DATANODE-START" : ["RANGER_USERSYNC-START"],
    "NAMENODE-START" : ["RANGER_USERSYNC-START"],
    "FALCON_SERVER-START": ["NAMENODE-START", "DATANODE-START"]
  }
}
