<?xml version="1.0"?>
<?xml-stylesheet type="text/xsl" href="configuration.xsl"?>
<!--
/**
 * Licensed to the Apache Software Foundation (ASF) under one
 * or more contributor license agreements.  See the NOTICE file
 * distributed with this work for additional information
 * regarding copyright ownership.  The ASF licenses this file
 * to you under the Apache License, Version 2.0 (the
 * "License"); you may not use this file except in compliance
 * with the License.  You may obtain a copy of the License at
 *
 *     http://www.apache.org/licenses/LICENSE-2.0
 *
 * Unless required by applicable law or agreed to in writing, software
 * distributed under the License is distributed on an "AS IS" BASIS,
 * WITHOUT WARRANTIES OR CONDITIONS OF ANY KIND, either express or implied.
 * See the License for the specific language governing permissions and
 * limitations under the License.
 */
-->
<configuration>
  <property>
    <name>ams.zookeeper.keytab</name>
    <value></value>
    <value-attributes>
      <empty-value-valid>true</empty-value-valid>
    </value-attributes>
  </property>
  <property>
    <name>ams.zookeeper.principal</name>
    <value></value>
    <value-attributes>
      <empty-value-valid>true</empty-value-valid>
    </value-attributes>
  </property>
  <property>
    <name>hadoop.security.authentication</name>
    <value></value>
    <value-attributes>
      <empty-value-valid>true</empty-value-valid>
    </value-attributes>
  </property>
  <property>
    <name>hbase.coprocessor.master.classes</name>
    <value></value>
    <value-attributes>
      <empty-value-valid>true</empty-value-valid>
    </value-attributes>
  </property>
  <property>
    <name>hbase.coprocessor.region.classes</name>
    <value></value>
    <value-attributes>
      <empty-value-valid>true</empty-value-valid>
    </value-attributes>
  </property>
  <property>
    <name>hbase.master.kerberos.principal</name>
    <value></value>
    <value-attributes>
      <empty-value-valid>true</empty-value-valid>
    </value-attributes>
  </property>
  <property>
    <name>hbase.master.keytab.file</name>
    <value></value>
    <value-attributes>
      <empty-value-valid>true</empty-value-valid>
    </value-attributes>
  </property>
  <property>
    <name>hbase.myclient.keytab</name>
    <value></value>
    <value-attributes>
      <empty-value-valid>true</empty-value-valid>
    </value-attributes>
  </property>
  <property>
    <name>hbase.myclient.principal</name>
    <value></value>
    <value-attributes>
      <empty-value-valid>true</empty-value-valid>
    </value-attributes>
  </property>
  <property>
    <name>hbase.regionserver.kerberos.principal</name>
    <value></value>
    <value-attributes>
      <empty-value-valid>true</empty-value-valid>
    </value-attributes>
  </property>
  <property>
    <name>hbase.regionserver.keytab.file</name>
    <value></value>
    <value-attributes>
      <empty-value-valid>true</empty-value-valid>
    </value-attributes>
  </property>
  <property>
    <name>hbase.security.authentication</name>
    <value></value>
    <value-attributes>
      <empty-value-valid>true</empty-value-valid>
    </value-attributes>
  </property>
  <property>
    <name>hbase.security.authorization</name>
    <value></value>
    <value-attributes>
      <empty-value-valid>true</empty-value-valid>
    </value-attributes>
  </property>
  <property>
    <name>hbase.zookeeper.property.authProvider.1</name>
    <value></value>
    <value-attributes>
      <empty-value-valid>true</empty-value-valid>
    </value-attributes>
  </property>
  <property>
    <name>hbase.zookeeper.property.jaasLoginRenew</name>
    <value></value>
    <value-attributes>
      <empty-value-valid>true</empty-value-valid>
    </value-attributes>
  </property>
  <property>
    <name>hbase.zookeeper.property.kerberos.removeHostFromPrincipal</name>
    <value></value>
    <value-attributes>
      <empty-value-valid>true</empty-value-valid>
    </value-attributes>
  </property>
  <property>
    <name>hbase.zookeeper.property.kerberos.removeRealmFromPrincipal</name>
    <value></value>
    <value-attributes>
      <empty-value-valid>true</empty-value-valid>
    </value-attributes>
  </property>
</configuration>
