{"jobs": [
  {
    "confPath": "hdfs://ip-10-114-221-210\\.ec2\\.internal:8020/tmp/hadoop-mapred/mapred/staging/ambari_qa/\\.staging/job_201211151748_0001/job\\.xml",
    "elapsedTime": 41103,
    "inputBytes": 1777,
    "jobId": "job_201211151748_0001",
    "jobName": "word count",
    "maps": 1,
    "outputBytes": 1736,
    "reduces": 1,
    "status": "SUCCESS",
    "submitTime": 1353019777592,
    "userName": "ambari_qa",
    "workflowEntityName": "X",
    "workflowId": "mr_201211151748_0001"
  }
]}